{
  "metadata": {
    "version": "1.19.0",
    "generatedAt": "2026-07-14T05:00:32.718607965Z",
    "templateType": "trip_l",
    "propertyId": "d7cc2947-8744-4e34-ac08-fe100d9bf567",
    "homepageId": "c18f2b14-16f5-49b6-b7d4-f559ad5632a4"
  },
  "property": {
    "id": "d7cc2947-8744-4e34-ac08-fe100d9bf567",
    "name": "가평 온하루펜션",
    "nameEn": "Gapyeong Onharu Pension",
    "description": "탁 트인 가평의 풍경과 맑은 계곡, 프라이빗 바베큐가 어우러진 공간에서 사랑하는 사람들과 여유롭고 특별한 하루를 완성해 보세요.",
    "subtitle": "",
    "address": "경기 가평군 북면 가화로 1720-23 가평 온하루펜션",
    "latitude": 37.9100664869136,
    "longitude": 127.495728746567,
    "contactPhone": "010-3086-3365",
    "contactEmail": "",
    "checkin": "14:00",
    "checkout": "12:00",
    "checkInOutInfo": "[입퇴실안내]\n- 입실: 14시 00분\n- 퇴실: 12시 00분\n- 입실 마감시간: 23시 00분",
    "usageGuide": "[입퇴실안내]\n- 입실: 14시 00분\n- 퇴실: 12시 00분\n- 입실 마감시간: 23시 00분\n\n[인원추가요금]\n※ 24개월 유아 무료, 최대인원 포함\n※ 14세 미만 아동 1명 무료\n\n[개별바베큐]\n- 이용 객실: 전 객실\n- 이용 장소: 개별 객실 앞\n- 바베큐 형태: 숯불\n- 제공 구성: 숯, 그릴, 채소(상추/깻잎) 등\n※ 펜션 주인이 직접 정성껏 재배한 채소(상추, 깻잎)를 무료로 제공해 드립니다.\n- 이용 요금: 4인 20,000원(1박기준/현장결제)\n- 신청 시간: 제한없음\n- 이용 시간: 제한없음\n- 우천 시: 이용 가능\n- 동계 시: 이용 가능\n- 강풍 시: 이용 불가\n※ 바베큐 이용 시 원활한 준비를 위해 이용 1시간 전까지 사전 요청 부탁드립니다.\n\n[공용수영장]\n- 이용 객실: 전 객실\n- 운영 계절: 하절기\n- 운영 기간: 6월 1일 ~ 9월 30일\n- 온도: 냉수\n- 이용 요금: 무료\n- 이용 시간: 14:00 ~ 22:00\n- 이용 복장: 제한없음\n- 수영장 크기: 4m x 6m\n\n[부대시설]\n[객실에서 즐기는 노래방]\n- 이용 요금: 50,000원 (1박기준/현장결제)\n- 이용 시간: 입실 후 ~ 21:00\n※ 요청 시 이동식 노래방 기기를 객실로 제공해 드립니다.\n※ 이용을 원하시는 경우 펜션으로 문의해 주시기 바랍니다.\n\n[펜션 내 음식점]\n- 메뉴: 백숙, 도리탕. 육개장 등\n※ 식사 이용 관련 사항은 펜션으로 문의해 주시기 바랍니다.\n\n[편의 및 주변 시설]\n- 와이파이 보유\n- 화재감지기 보유\n- 일산화탄소감지기 보유\n- 엘레베이터 미보유\n- 인근 200m 이내 명지산 계곡 (수영, 낚시 가능)\n\n[주차장]\n- 주차장 보유\n- 이용 요금: 무료\n- 주차 대수: 총 10대\n- 전기차 충전기 이용 불가",
    "reservationGuide": "",
    "province": "도/시",
    "city": "시/군/구",
    "domain": "onharu.co.kr",
    "realtimeBookingId": "https://www.bookingplay.co.kr/booking/1/12863",
    "ybsId": "",
    "amenities": [
      "흡연구역(지정장소)",
      "주차장"
    ],
    "nearbyAttractions": [
      "포레스트뷰(산)",
      "계곡인접"
    ],
    "services": [ ],
    "propertyThemes": [ ],
    "propertyTypes": [ ],
    "businessInfo": {
      "businessName": "온하루",
      "businessNumber": "598-28-01913",
      "representativeName": "이영수",
      "businessAddress": "경기도 가평군 북면 가화로 1720-23",
      "businessPhone": "",
      "businessEmail": "lys350412@naver.com",
      "businessType": "corporate",
      "businessCategory": "숙박",
      "eCommerceRegistrationNumber": ""
    },
    "contractInfo": {
      "contractStartDate": "2025-09-10T00:00:00.000Z",
      "contractEndDate": "2025-09-12T00:00:00.000Z",
      "contractStatus": "active",
      "contactName": "담당자명",
      "contactEmail": "담당자 이메일",
      "contactPhone": "담당자 전화번호",
      "paymentTerms": null,
      "cancellationPolicy": null,
      "bankName": "은행명",
      "accountNumber": "계좌번호",
      "accountHolder": "예금주",
      "commissionRate": 0,
      "securityDeposit": 0
    },
    "facilities": [
      {
        "id": "5992e28f-88fc-4bba-be96-1ec805550cd5",
        "name": "공용수영장",
        "description": "햇살 아래에서 가볍게 물에 몸을 맡기며\n여유롭게 흐르는 시간을 느껴보세요.\n시원한 물결 속에서 편안한 휴식을 즐길 수 있습니다.",
        "usageGuide": "- 이용 객실: 전 객실\n- 운영 계절: 하절기\n- 운영 기간: 6월 1일 ~ 9월 30일\n- 온도: 냉수\n- 이용 요금: 무료\n- 이용 시간: 14:00 ~ 22:00\n- 이용 복장: 제한없음\n- 수영장 크기: 4m x 6m",
        "displayOrder": 0,
        "images": [
          {
            "id": "0692ba26-05fb-4f38-957d-8f99b51d4880",
            "url": "https://jlnjajtcnyqupfaqjerz.supabase.co/storage/v1/object/public/app-images/facility/5992e28f-88fc-4bba-be96-1ec805550cd5/main/1783993453551-hzf30t3o7y.jpg",
            "sortOrder": 0,
            "description": "",
            "isSelected": true,
            "blockId": null
          },
          {
            "id": "619e996f-6e97-49b7-bc0f-e380e7ab24a5",
            "url": "https://jlnjajtcnyqupfaqjerz.supabase.co/storage/v1/object/public/app-images/facility/5992e28f-88fc-4bba-be96-1ec805550cd5/main/1783993453794-61d9hr9zfm.jpg",
            "sortOrder": 1,
            "description": "",
            "isSelected": true,
            "blockId": null
          },
          {
            "id": "eb5fcde3-c32b-430d-90e3-0cc4e4f9564c",
            "url": "https://jlnjajtcnyqupfaqjerz.supabase.co/storage/v1/object/public/app-images/facility/5992e28f-88fc-4bba-be96-1ec805550cd5/main/1783993453794-cg488ergwo.jpg",
            "sortOrder": 2,
            "description": "",
            "isSelected": true,
            "blockId": null
          },
          {
            "id": "cca1ebd9-3f79-4d76-b48b-88f9fdc397d4",
            "url": "https://jlnjajtcnyqupfaqjerz.supabase.co/storage/v1/object/public/app-images/facility/5992e28f-88fc-4bba-be96-1ec805550cd5/main/1783993453558-acz3tfgv1f.jpg",
            "sortOrder": 3,
            "description": "",
            "isSelected": true,
            "blockId": null
          },
          {
            "id": "2769d9d0-daab-4941-ac89-6e3eccd6d000",
            "url": "https://jlnjajtcnyqupfaqjerz.supabase.co/storage/v1/object/public/app-images/facility/5992e28f-88fc-4bba-be96-1ec805550cd5/main/1783993453562-hcd4e77kvv.jpg",
            "sortOrder": 4,
            "description": "",
            "isSelected": true,
            "blockId": null
          }
        ]
      },
      {
        "id": "7732b955-3358-4312-b716-d602192010d1",
        "name": "개별바베큐",
        "description": "여유로운 공간에서 즐기는 식사 시간은\n단순한 한 끼를 넘어 특별한 기억으로 남습니다.\n편안한 분위기 속에서 온전한 시간을 보내보세요.",
        "usageGuide": "- 이용 객실: 전 객실\n- 이용 장소: 개별 객실 앞\n- 바베큐 형태: 숯불\n- 제공 구성: 숯, 그릴, 채소(상추/깻잎) 등\n※ 펜션 주인이 직접 정성껏 재배한 채소(상추, 깻잎)를 무료로 제공해 드립니다.\n- 이용 요금: 4인 20,000원(1박기준/현장결제)\n- 신청 시간: 제한없음\n- 이용 시간: 제한없음\n- 우천 시: 이용 가능\n- 동계 시: 이용 가능\n- 강풍 시: 이용 불가\n※ 바베큐 이용 시 원활한 준비를 위해 이용 1시간 전까지 사전 요청 부탁드립니다.",
        "displayOrder": 1,
        "images": [
          {
            "id": "0f1e4595-0cc9-47bf-b3f6-77c9535f1be5",
            "url": "https://jlnjajtcnyqupfaqjerz.supabase.co/storage/v1/object/public/app-images/facility/7732b955-3358-4312-b716-d602192010d1/main/1783993455825-goflve4w4s.jpg",
            "sortOrder": 0,
            "description": "",
            "isSelected": true,
            "blockId": null
          },
          {
            "id": "c3579bcd-7dd5-4075-bfa9-2bf55611c4c5",
            "url": "https://jlnjajtcnyqupfaqjerz.supabase.co/storage/v1/object/public/app-images/facility/7732b955-3358-4312-b716-d602192010d1/main/1783993455819-y0hkfj6z2u.jpg",
            "sortOrder": 1,
            "description": "",
            "isSelected": true,
            "blockId": null
          },
          {
            "id": "b68865ad-417d-4596-9899-b7514d29b668",
            "url": "https://jlnjajtcnyqupfaqjerz.supabase.co/storage/v1/object/public/app-images/facility/7732b955-3358-4312-b716-d602192010d1/main/1783993455826-mwx0yoc33c.jpg",
            "sortOrder": 2,
            "description": "",
            "isSelected": true,
            "blockId": null
          }
        ]
      },
      {
        "id": "31d12c77-a27d-4092-9b3e-8f5a2cd31ba8",
        "name": "부대시설",
        "description": "맛있는 식사와 다양한 즐길 거리가 어우러져\n머무는 시간까지 더욱 특별한 추억으로 이어집니다.",
        "usageGuide": "[객실에서 즐기는 노래방]\n- 이용 요금: 50,000원 (1박기준/현장결제)\n- 이용 시간: 입실 후 ~ 21:00\n※ 요청 시 이동식 노래방 기기를 객실로 제공해 드립니다.\n※ 이용을 원하시는 경우 펜션으로 문의해 주시기 바랍니다.\n\n[펜션 내 음식점]\n- 메뉴: 백숙, 도리탕. 육개장 등\n※ 식사 이용 관련 사항은 펜션으로 문의해 주시기 바랍니다.",
        "displayOrder": 2,
        "images": [
          {
            "id": "936a673e-84b3-41e1-97db-3da2b9841329",
            "url": "https://jlnjajtcnyqupfaqjerz.supabase.co/storage/v1/object/public/app-images/facility/31d12c77-a27d-4092-9b3e-8f5a2cd31ba8/main/1783993457916-0bhflo9pc6.jpg",
            "sortOrder": 0,
            "description": "",
            "isSelected": true,
            "blockId": null
          },
          {
            "id": "5a468bd2-676e-42c2-864b-fe752340ea49",
            "url": "https://jlnjajtcnyqupfaqjerz.supabase.co/storage/v1/object/public/app-images/facility/31d12c77-a27d-4092-9b3e-8f5a2cd31ba8/main/1783993457921-bw20eq0cul.jpg",
            "sortOrder": 1,
            "description": "",
            "isSelected": true,
            "blockId": null
          },
          {
            "id": "092ed831-7c94-4d33-92b6-c08a145ad931",
            "url": "https://jlnjajtcnyqupfaqjerz.supabase.co/storage/v1/object/public/app-images/facility/31d12c77-a27d-4092-9b3e-8f5a2cd31ba8/main/1783993457915-n0jpfnlv61.jpg",
            "sortOrder": 2,
            "description": "",
            "isSelected": true,
            "blockId": null
          },
          {
            "id": "47dad08f-66af-411b-b2ad-a4723f3ca96d",
            "url": "https://jlnjajtcnyqupfaqjerz.supabase.co/storage/v1/object/public/app-images/facility/31d12c77-a27d-4092-9b3e-8f5a2cd31ba8/main/1783993457923-5x5ft9zmwr.jpg",
            "sortOrder": 3,
            "description": "",
            "isSelected": true,
            "blockId": null
          }
        ]
      },
      {
        "id": "da2185b1-3a7f-4e28-a08b-4bf77eb0364c",
        "name": "편의 및 주변 시설",
        "description": "머무는 모든 순간이 편안하게 이어질 수 있도록\n세심한 준비로 공간의 완성도를 더했습니다.\n부담 없이 쉬어갈 수 있는 시간을 제공합니다.",
        "usageGuide": "- 와이파이 보유\n- 화재감지기 보유\n- 일산화탄소감지기 보유\n- 엘레베이터 미보유\n- 인근 200m 이내 명지산 계곡 (수영, 낚시 가능)",
        "displayOrder": 3,
        "images": [
          {
            "id": "7e32cb0d-18a8-4af3-bd41-2de47d40b54b",
            "url": "https://jlnjajtcnyqupfaqjerz.supabase.co/storage/v1/object/public/app-images/facility/da2185b1-3a7f-4e28-a08b-4bf77eb0364c/main/1783998151913-vqek3e5pmh.jpg",
            "sortOrder": 0,
            "description": "",
            "isSelected": true,
            "blockId": null
          },
          {
            "id": "c66a7427-face-4224-8740-62485ac48bc2",
            "url": "https://jlnjajtcnyqupfaqjerz.supabase.co/storage/v1/object/public/app-images/facility/da2185b1-3a7f-4e28-a08b-4bf77eb0364c/main/1783998151915-o3mx6ak4g4.jpg",
            "sortOrder": 1,
            "description": "",
            "isSelected": true,
            "blockId": null
          },
          {
            "id": "6a88736d-a2fc-4eeb-90a2-0c8173107cf9",
            "url": "https://jlnjajtcnyqupfaqjerz.supabase.co/storage/v1/object/public/app-images/facility/da2185b1-3a7f-4e28-a08b-4bf77eb0364c/main/1783998151990-dkusowtb54.jpg",
            "sortOrder": 2,
            "description": "",
            "isSelected": true,
            "blockId": null
          },
          {
            "id": "37816c00-8f75-47ab-9066-3556cab364b1",
            "url": "https://jlnjajtcnyqupfaqjerz.supabase.co/storage/v1/object/public/app-images/facility/da2185b1-3a7f-4e28-a08b-4bf77eb0364c/main/1783998152004-e3l7rohve8.jpg",
            "sortOrder": 3,
            "description": "",
            "isSelected": true,
            "blockId": null
          }
        ]
      }
    ],
    "refundPolicies": [
      {
        "refundProcessingDays": 10,
        "refundRate": 100
      },
      {
        "refundProcessingDays": 9,
        "refundRate": 90
      },
      {
        "refundProcessingDays": 8,
        "refundRate": 80
      },
      {
        "refundProcessingDays": 7,
        "refundRate": 70
      },
      {
        "refundProcessingDays": 6,
        "refundRate": 60
      },
      {
        "refundProcessingDays": 5,
        "refundRate": 50
      },
      {
        "refundProcessingDays": 4,
        "refundRate": 40
      },
      {
        "refundProcessingDays": 3,
        "refundRate": 30
      },
      {
        "refundProcessingDays": 2,
        "refundRate": 20
      },
      {
        "refundProcessingDays": 1,
        "refundRate": 10
      },
      {
        "refundProcessingDays": 0,
        "refundRate": 0
      }
    ],
    "refundSettings": {
      "customerRefundNotice": "",
      "immediateRefundEnabled": true,
      "immediateRefundTimeLimit": "60",
      "immediateRefundMinuteLimit": "10",
      "sameDayReservationHourLimit": "0"
    },
    "images": [
      {
        "thumbnail": [
          {
            "id": "7828fa34-825d-47a8-8323-3b4a750c99be",
            "url": "https://bookingplay-media.s3.amazonaws.com/item_images/2026/07/14/Ca3FLqU6l0ck.jpg",
            "sortOrder": 0,
            "description": "",
            "isSelected": true,
            "blockId": null
          }
        ],
        "exterior": [
          {
            "id": "39cd8f28-2983-4a22-916f-f58eebbf7621",
            "url": "https://bookingplay-media.s3.amazonaws.com/item_images/2026/07/14/Qw8EILept7Oa.jpg",
            "sortOrder": 0,
            "description": "",
            "isSelected": true,
            "blockId": null
          },
          {
            "id": "8df78f2d-c3cd-43b5-83bc-52309a39b5c9",
            "url": "https://bookingplay-media.s3.amazonaws.com/item_images/2026/07/14/Yt0AViNxsR9j.jpg",
            "sortOrder": 1,
            "description": "",
            "isSelected": true,
            "blockId": null
          },
          {
            "id": "8ed292e8-2676-40f7-ab1c-e2a2bb12e76b",
            "url": "https://bookingplay-media.s3.amazonaws.com/item_images/2026/07/14/PflVQqAF98LY.jpg",
            "sortOrder": 2,
            "description": "",
            "isSelected": true,
            "blockId": null
          },
          {
            "id": "d17d8d4f-dda5-4a52-91e3-326dd29bfb2a",
            "url": "https://bookingplay-media.s3.amazonaws.com/item_images/2026/07/14/nJ2NbKFkLQIp.jpg",
            "sortOrder": 3,
            "description": "",
            "isSelected": true,
            "blockId": null
          },
          {
            "id": "4563bb06-0a70-4133-9c6e-20fe9f8453f3",
            "url": "https://bookingplay-media.s3.amazonaws.com/item_images/2026/07/14/eSJ0s2GOh7I8.jpg",
            "sortOrder": 4,
            "description": "",
            "isSelected": true,
            "blockId": null
          },
          {
            "id": "10374b2c-c63a-4e76-99b7-915c71d4c0be",
            "url": "https://bookingplay-media.s3.amazonaws.com/item_images/2026/07/14/3oP820sG6Jht.jpg",
            "sortOrder": 5,
            "description": "",
            "isSelected": true,
            "blockId": null
          },
          {
            "id": "eeb41e06-7fe9-4ee7-9c8b-a0b652ce4744",
            "url": "https://bookingplay-media.s3.amazonaws.com/item_images/2026/07/14/K3sTbcXOCpx7.jpg",
            "sortOrder": 6,
            "description": "",
            "isSelected": true,
            "blockId": null
          },
          {
            "id": "bd54d5ea-d7ee-46c6-87ec-8b9729b956d4",
            "url": "https://bookingplay-media.s3.amazonaws.com/item_images/2026/07/14/nQSjFX3B5OE9.jpg",
            "sortOrder": 7,
            "description": "",
            "isSelected": true,
            "blockId": null
          },
          {
            "id": "0a53e6f2-97ce-47da-98fe-49282664c4e3",
            "url": "https://bookingplay-media.s3.amazonaws.com/item_images/2026/07/14/MAt5BalYb4Og.jpg",
            "sortOrder": 8,
            "description": "",
            "isSelected": true,
            "blockId": null
          }
        ],
        "surrounding": [ ],
        "commonArea": [ ]
      }
    ]
  },
  "rooms": [
    {
      "id": "c0ef986b-42eb-4923-ae70-f5bc6e24d132",
      "name": "일반실 1(개별 바베큐)",
      "description": "독채형, 거실1+침대룸(퀸침대1)+침대룸(퀸침대1)+주방1+화장실1\r\n산전망, 20평\r\n욕실용품,남녀공용,TV,금연,냉장고,에어컨,전기밥솥,취사시설/도구,타월,단체,드라이기,가족실,화재 감지기,일산화탄소 감지기,식탁",
      "roomInfo": "",
      "usageGuide": "",
      "group": null,
      "size": 66.12,
      "baseOccupancy": 4,
      "maxOccupancy": 10,
      "totalRoomCount": {
        "bedroom": 2,
        "bathroom": 1,
        "livingRoom": 1,
        "ondol": 0,
        "kitchen": 1
      },
      "bedTypes": [
        "퀸 베드"
      ],
      "bedConfigs": [
        {
          "roomIndex": 1,
          "roomKind": "bedroom",
          "bedCount": {
            "double": 0,
            "single": 0,
            "bunkBed": 0,
            "queen": 1,
            "king": 0,
            "family": 0,
            "sofaBed": 0,
            "beddingSet": 0
          }
        },
        {
          "roomIndex": 2,
          "roomKind": "bedroom",
          "bedCount": {
            "double": 0,
            "single": 0,
            "bunkBed": 0,
            "queen": 1,
            "king": 0,
            "family": 0,
            "sofaBed": 0,
            "beddingSet": 0
          }
        }
      ],
      "amenities": [
        "식탁",
        "일산화탄소 감지기",
        "화재 감지기",
        "가족실",
        "헤어드라이어",
        "단체",
        "수건",
        "취사시설/도구",
        "전기밥솥",
        "에어컨",
        "냉장고",
        "금연",
        "TV",
        "남녀공용",
        "욕실용품"
      ],
      "roomViews": [
        "마운틴뷰"
      ],
      "roomStructures": [
        "독채"
      ],
      "status": "active",
      "timeSettings": {
        "timeSettingType": "property",
        "checkin": "14:00",
        "checkout": "12:00",
        "checkinDeadline": "23:00"
      },
      "roomOptions": {
        "petState": "N",
        "poolState": "Y",
        "barbecueState": "Y"
      },
      "images": [
        {
          "thumbnail": [
            {
              "id": "2ab3173b-33aa-4e8b-9b8e-b203dd2f09c3",
              "url": "https://bookingplay-media.s3.amazonaws.com/room_images/2026/07/14/C5SEbwv4coNh.jpg",
              "sortOrder": 1,
              "description": "",
              "isSelected": true,
              "blockId": null
            }
          ],
          "interior": [
            {
              "id": "b044157e-aec8-44b0-b8ee-b22cb02f8d15",
              "url": "https://bookingplay-media.s3.amazonaws.com/room_images/2026/07/14/mT6K9rJcpgvL.jpg",
              "sortOrder": 2,
              "description": "",
              "isSelected": true,
              "blockId": null
            },
            {
              "id": "b060ddbc-4763-4c9b-8110-5677abe3251e",
              "url": "https://bookingplay-media.s3.amazonaws.com/room_images/2026/07/14/ADpIOQxPuq1N.jpg",
              "sortOrder": 3,
              "description": "",
              "isSelected": true,
              "blockId": null
            },
            {
              "id": "d6a80392-e9df-41dc-a74f-21ac22aa6599",
              "url": "https://bookingplay-media.s3.amazonaws.com/room_images/2026/07/14/8pO6nRdiNjTQ.jpg",
              "sortOrder": 4,
              "description": "",
              "isSelected": true,
              "blockId": null
            },
            {
              "id": "9d25b0e5-e203-489f-b074-925c834b11bd",
              "url": "https://bookingplay-media.s3.amazonaws.com/room_images/2026/07/14/8cAwEjCN6aOX.jpg",
              "sortOrder": 5,
              "description": "",
              "isSelected": true,
              "blockId": null
            },
            {
              "id": "927c71a8-eefa-43cd-9799-8851da1bfa36",
              "url": "https://bookingplay-media.s3.amazonaws.com/room_images/2026/07/14/A3XKjZNG9oUm.jpg",
              "sortOrder": 6,
              "description": "",
              "isSelected": true,
              "blockId": null
            },
            {
              "id": "6859dda0-5bbc-42c9-aa1e-e38e7ad531fd",
              "url": "https://bookingplay-media.s3.amazonaws.com/room_images/2026/07/14/1aJkzLbIh75r.jpg",
              "sortOrder": 7,
              "description": "",
              "isSelected": true,
              "blockId": null
            },
            {
              "id": "2be8eade-6106-41cf-956a-9b1f0a1848c1",
              "url": "https://bookingplay-media.s3.amazonaws.com/room_images/2026/07/14/24aL1UEvSAJw.jpg",
              "sortOrder": 8,
              "description": "",
              "isSelected": true,
              "blockId": null
            },
            {
              "id": "94c01b69-07c7-47d9-bb89-9020af4f45f9",
              "url": "https://bookingplay-media.s3.amazonaws.com/room_images/2026/07/14/peRTQiqy4CPo.jpg",
              "sortOrder": 9,
              "description": "",
              "isSelected": true,
              "blockId": null
            },
            {
              "id": "b4349f0f-928b-4228-ae3e-1ebe5da283bd",
              "url": "https://bookingplay-media.s3.amazonaws.com/room_images/2026/07/14/ktSJ2FsHLK4Q.jpg",
              "sortOrder": 10,
              "description": "",
              "isSelected": true,
              "blockId": null
            },
            {
              "id": "1b071b42-4901-4666-85fc-5737b8717f0f",
              "url": "https://bookingplay-media.s3.amazonaws.com/room_images/2026/07/14/iXxt0gPw4Del.jpg",
              "sortOrder": 11,
              "description": "",
              "isSelected": true,
              "blockId": null
            },
            {
              "id": "d99880a5-91f7-4857-a10c-630314a40bc4",
              "url": "https://bookingplay-media.s3.amazonaws.com/room_images/2026/07/14/DLcIgfSmv4V8.jpg",
              "sortOrder": 12,
              "description": "",
              "isSelected": true,
              "blockId": null
            },
            {
              "id": "e34dec09-734e-4251-beb7-c8a3bbdd0940",
              "url": "https://bookingplay-media.s3.amazonaws.com/room_images/2026/07/14/7wJ2sla8vXo3.jpg",
              "sortOrder": 13,
              "description": "",
              "isSelected": true,
              "blockId": null
            },
            {
              "id": "a4187bf9-3c6a-4c1f-af87-8cdb4b128b30",
              "url": "https://bookingplay-media.s3.amazonaws.com/room_images/2026/07/14/hrMHT9C41lx2.jpg",
              "sortOrder": 14,
              "description": "",
              "isSelected": true,
              "blockId": null
            },
            {
              "id": "516995ad-903b-48ba-b673-2e7ef4a89560",
              "url": "https://bookingplay-media.s3.amazonaws.com/room_images/2026/07/14/pec5EUCLZsx1.jpg",
              "sortOrder": 15,
              "description": "",
              "isSelected": true,
              "blockId": null
            }
          ],
          "exterior": [ ]
        }
      ],
      "displayOrder": 1
    },
    {
      "id": "2b5810fe-fc6e-446f-b84d-02f3ae2cfca0",
      "name": "일반실 2(개별 바베큐)",
      "description": "독채형, 거실1+침대룸(퀸침대1)+침대룸(퀸침대1)+주방1+화장실1\r\n산전망, 20평\r\n욕실용품,남녀공용,TV,금연,냉장고,에어컨,전기밥솥,취사시설/도구,타월,단체,드라이기,가족실,화재 감지기,일산화탄소 감지기,식탁",
      "roomInfo": "",
      "usageGuide": "",
      "group": null,
      "size": 49.59,
      "baseOccupancy": 2,
      "maxOccupancy": 6,
      "totalRoomCount": {
        "bedroom": 1,
        "bathroom": 1,
        "livingRoom": 1,
        "ondol": 0,
        "kitchen": 1
      },
      "bedTypes": [
        "퀸 베드"
      ],
      "bedConfigs": [
        {
          "roomIndex": 1,
          "roomKind": "bedroom",
          "bedCount": {
            "double": 0,
            "single": 0,
            "bunkBed": 0,
            "queen": 1,
            "king": 0,
            "family": 0,
            "sofaBed": 0,
            "beddingSet": 0
          }
        }
      ],
      "amenities": [
        "식탁",
        "일산화탄소 감지기",
        "화재 감지기",
        "가족실",
        "헤어드라이어",
        "단체",
        "수건",
        "취사시설/도구",
        "전기밥솥",
        "에어컨",
        "냉장고",
        "금연",
        "TV",
        "남녀공용",
        "욕실용품"
      ],
      "roomViews": [
        "마운틴뷰"
      ],
      "roomStructures": [
        "독채"
      ],
      "status": "active",
      "timeSettings": {
        "timeSettingType": "property",
        "checkin": "14:00",
        "checkout": "12:00",
        "checkinDeadline": "23:00"
      },
      "roomOptions": {
        "petState": "N",
        "poolState": "Y",
        "barbecueState": "Y"
      },
      "images": [
        {
          "thumbnail": [
            {
              "id": "9bfe529f-e006-4b06-a29e-b3b0a967f879",
              "url": "https://bookingplay-media.s3.amazonaws.com/room_images/2026/07/14/pPsYbeG1lafv.jpg",
              "sortOrder": 1,
              "description": "",
              "isSelected": true,
              "blockId": null
            }
          ],
          "interior": [
            {
              "id": "62970886-7aaf-453e-8370-2e586e041e4f",
              "url": "https://bookingplay-media.s3.amazonaws.com/room_images/2026/07/14/WoiUEqhKPnkb.jpg",
              "sortOrder": 2,
              "description": "",
              "isSelected": true,
              "blockId": null
            },
            {
              "id": "acd85aaa-87a3-4d60-8e1b-57efbb1edefb",
              "url": "https://bookingplay-media.s3.amazonaws.com/room_images/2026/07/14/9U0KBleQ2si3.jpg",
              "sortOrder": 3,
              "description": "",
              "isSelected": true,
              "blockId": null
            },
            {
              "id": "9c11acf2-9d61-476c-b5d8-1f39736285e1",
              "url": "https://bookingplay-media.s3.amazonaws.com/room_images/2026/07/14/8RZbg2cK5opE.jpg",
              "sortOrder": 4,
              "description": "",
              "isSelected": true,
              "blockId": null
            },
            {
              "id": "09b6c91c-f762-4057-b13a-4feb2c642d8c",
              "url": "https://bookingplay-media.s3.amazonaws.com/room_images/2026/07/14/Lu6oe98vlShc.jpg",
              "sortOrder": 5,
              "description": "",
              "isSelected": true,
              "blockId": null
            },
            {
              "id": "73fe5e5a-d8ea-43f9-a9b9-9dfc5f804ab2",
              "url": "https://bookingplay-media.s3.amazonaws.com/room_images/2026/07/14/ix8oV9ajXpGN.jpg",
              "sortOrder": 6,
              "description": "",
              "isSelected": true,
              "blockId": null
            },
            {
              "id": "8c58f0a3-3fea-45ec-872c-27978ea88ae4",
              "url": "https://bookingplay-media.s3.amazonaws.com/room_images/2026/07/14/kEfJptujbvSQ.jpg",
              "sortOrder": 7,
              "description": "",
              "isSelected": true,
              "blockId": null
            },
            {
              "id": "98639832-6b5d-41c1-9c60-40bc5f64dfdc",
              "url": "https://bookingplay-media.s3.amazonaws.com/room_images/2026/07/14/9uQlscw7S3Pa.jpg",
              "sortOrder": 8,
              "description": "",
              "isSelected": true,
              "blockId": null
            },
            {
              "id": "8d680368-13e8-4626-9ad7-c0a2f80cdce9",
              "url": "https://bookingplay-media.s3.amazonaws.com/room_images/2026/07/14/0OIcrKYduEAD.jpg",
              "sortOrder": 9,
              "description": "",
              "isSelected": true,
              "blockId": null
            },
            {
              "id": "1d601b67-83fe-4987-9bb7-b210e3b791a5",
              "url": "https://bookingplay-media.s3.amazonaws.com/room_images/2026/07/14/BgGIWETeCjqa.jpg",
              "sortOrder": 10,
              "description": "",
              "isSelected": true,
              "blockId": null
            },
            {
              "id": "0a4356f2-4b60-43c2-a637-f1c76a4eeeec",
              "url": "https://bookingplay-media.s3.amazonaws.com/room_images/2026/07/14/o6wevFNrA3tj.jpg",
              "sortOrder": 11,
              "description": "",
              "isSelected": true,
              "blockId": null
            }
          ],
          "exterior": [ ]
        }
      ],
      "displayOrder": 2
    },
    {
      "id": "6cbb9513-a1bc-4dc3-a341-ff7c057ae68d",
      "name": "일반실 3(개별 바베큐)",
      "description": "분리형, 거실1+온돌룸(침구세트6)+주방1+화장실1\r\n15평\r\n욕실용품,남녀공용,TV,금연,냉장고,에어컨,전기밥솥,취사시설/도구,타월,단체,드라이기,가족실,화재 감지기,일산화탄소 감지기,식탁",
      "roomInfo": "",
      "usageGuide": "",
      "group": null,
      "size": 49.59,
      "baseOccupancy": 4,
      "maxOccupancy": 10,
      "totalRoomCount": {
        "bedroom": 0,
        "bathroom": 1,
        "livingRoom": 1,
        "ondol": 1,
        "kitchen": 1
      },
      "bedTypes": [
        "바닥침구"
      ],
      "bedConfigs": [
        {
          "roomIndex": 1,
          "roomKind": "ondol",
          "bedCount": {
            "double": 0,
            "single": 0,
            "bunkBed": 0,
            "queen": 0,
            "king": 0,
            "family": 0,
            "sofaBed": 0,
            "beddingSet": 6
          }
        }
      ],
      "amenities": [
        "식탁",
        "일산화탄소 감지기",
        "화재 감지기",
        "가족실",
        "헤어드라이어",
        "단체",
        "수건",
        "취사시설/도구",
        "전기밥솥",
        "에어컨",
        "냉장고",
        "금연",
        "TV",
        "남녀공용",
        "욕실용품"
      ],
      "roomViews": [ ],
      "roomStructures": [
        "분리형"
      ],
      "status": "active",
      "timeSettings": {
        "timeSettingType": "property",
        "checkin": "14:00",
        "checkout": "12:00",
        "checkinDeadline": "23:00"
      },
      "roomOptions": {
        "petState": "N",
        "poolState": "Y",
        "barbecueState": "Y"
      },
      "images": [
        {
          "thumbnail": [
            {
              "id": "8232627a-538e-4838-9b29-0893743dc1ef",
              "url": "https://bookingplay-media.s3.amazonaws.com/room_images/2026/07/14/GcWUC82YEmaj.jpg",
              "sortOrder": 1,
              "description": "",
              "isSelected": true,
              "blockId": null
            }
          ],
          "interior": [
            {
              "id": "4319f589-9a73-472d-b2ec-b0760f47217f",
              "url": "https://bookingplay-media.s3.amazonaws.com/room_images/2026/07/14/Dgsx1RQzoqHh.jpg",
              "sortOrder": 2,
              "description": "",
              "isSelected": true,
              "blockId": null
            },
            {
              "id": "55f23ba0-271a-46b7-937b-f07f0249d044",
              "url": "https://bookingplay-media.s3.amazonaws.com/room_images/2026/07/14/snGWcKEdOjzo.jpg",
              "sortOrder": 3,
              "description": "",
              "isSelected": true,
              "blockId": null
            },
            {
              "id": "d8f0442c-5321-4521-977e-5cfe9b3f9678",
              "url": "https://bookingplay-media.s3.amazonaws.com/room_images/2026/07/14/seWPyoiVmvjC.jpg",
              "sortOrder": 4,
              "description": "",
              "isSelected": true,
              "blockId": null
            },
            {
              "id": "29aaa502-80e0-4b9b-85ae-ab93ecb75ce9",
              "url": "https://bookingplay-media.s3.amazonaws.com/room_images/2026/07/14/y1Vl5tXKBURL.jpg",
              "sortOrder": 5,
              "description": "",
              "isSelected": true,
              "blockId": null
            },
            {
              "id": "2a6b896a-4035-4e45-b3b0-f70f3d5b5cfb",
              "url": "https://bookingplay-media.s3.amazonaws.com/room_images/2026/07/14/nOaiAB32HFrj.jpg",
              "sortOrder": 6,
              "description": "",
              "isSelected": true,
              "blockId": null
            }
          ],
          "exterior": [ ]
        }
      ],
      "displayOrder": 3
    }
  ],
  "homepage": {
    "id": "c18f2b14-16f5-49b6-b7d4-f559ad5632a4",
    "domain": "onharu.co.kr",
    "templateType": "trip_l",
    "images": [
      {
        "logo": [
          {
            "id": "8eae3ac0-fdd3-45cd-af66-60afc1d06d98",
            "url": "https://jlnjajtcnyqupfaqjerz.supabase.co/storage/v1/object/public/app-images/homepage/c18f2b14-16f5-49b6-b7d4-f559ad5632a4/logo/1783994228870-cuwkv4svr9.png",
            "sortOrder": 0,
            "description": "",
            "isSelected": true,
            "blockId": null
          }
        ]
      }
    ],
    "seo": {
      "title": "가평 온하루펜션",
      "description": "탁 트인 가평의 풍경과 맑은 계곡, 프라이빗 바베큐가 어우러진 공간에서 사랑하는 사람들과 여유롭고 특별한 하루를 완성해 보세요.",
      "keywords": "",
      "naverSiteVerification": "",
      "googleSiteVerification": ""
    },
    "socialLinks": {
      "facebook": null,
      "instagram": null,
      "blog": null,
      "youtube": null
    },
    "customFields": {
      "pages": {
        "index": {
          "sections": [
            {
              "hero": {
                "title": "자연이 전하는 편안한 쉼",
                "images": [
                  {
                    "id": "cc77b067-1cab-42d9-b0e3-1e56afae35a5",
                    "url": "https://jlnjajtcnyqupfaqjerz.supabase.co/storage/v1/object/public/app-images/homepage/c18f2b14-16f5-49b6-b7d4-f559ad5632a4/index_hero/1783995995149-2uro9zdl3q.jpg",
                    "sortOrder": 0,
                    "description": "",
                    "isSelected": true,
                    "blockId": null
                  },
                  {
                    "id": "04886f00-9788-4c3e-b7c7-bf8557f81a63",
                    "url": "https://jlnjajtcnyqupfaqjerz.supabase.co/storage/v1/object/public/app-images/homepage/c18f2b14-16f5-49b6-b7d4-f559ad5632a4/index_hero/1783995995235-7pypntenv0.jpg",
                    "sortOrder": 1,
                    "description": "머무는 순간",
                    "isSelected": true,
                    "blockId": null
                  },
                  {
                    "id": "2cb6d377-e082-41fc-87ce-0f4591211c2b",
                    "url": "https://jlnjajtcnyqupfaqjerz.supabase.co/storage/v1/object/public/app-images/homepage/c18f2b14-16f5-49b6-b7d4-f559ad5632a4/index_hero/1783995994943-zekapheai7.jpg",
                    "sortOrder": 2,
                    "description": "자연 속 하루",
                    "isSelected": true,
                    "blockId": null
                  },
                  {
                    "id": "ca03d793-cbb6-42d7-ad36-0ae80ef32e89",
                    "url": "https://jlnjajtcnyqupfaqjerz.supabase.co/storage/v1/object/public/app-images/homepage/c18f2b14-16f5-49b6-b7d4-f559ad5632a4/index_hero/1783995995231-vvuovc85nn.jpg",
                    "sortOrder": 3,
                    "description": "여유로운 시간",
                    "isSelected": true,
                    "blockId": null
                  },
                  {
                    "id": "d53be793-69d4-434c-9ef6-41ccc96d3b7b",
                    "url": "https://jlnjajtcnyqupfaqjerz.supabase.co/storage/v1/object/public/app-images/homepage/c18f2b14-16f5-49b6-b7d4-f559ad5632a4/index_hero/1783995994932-s0mmdkhdli.jpg",
                    "sortOrder": 4,
                    "description": "",
                    "isSelected": true,
                    "blockId": null
                  },
                  {
                    "id": "06cf8626-d5d2-4e00-b8cd-c5c34311902a",
                    "url": "https://jlnjajtcnyqupfaqjerz.supabase.co/storage/v1/object/public/app-images/homepage/c18f2b14-16f5-49b6-b7d4-f559ad5632a4/index_hero/1783995995127-jwrwxe2h68.jpg",
                    "sortOrder": 5,
                    "description": "",
                    "isSelected": true,
                    "blockId": null
                  },
                  {
                    "id": "42ffc919-80c6-4055-bc9b-b28c77ef3889",
                    "url": "https://jlnjajtcnyqupfaqjerz.supabase.co/storage/v1/object/public/app-images/homepage/c18f2b14-16f5-49b6-b7d4-f559ad5632a4/index_hero/1783995995163-lg9mm0ynuo.jpg",
                    "sortOrder": 6,
                    "description": "",
                    "isSelected": true,
                    "blockId": null
                  },
                  {
                    "id": "488cf5c9-e17f-4e12-8dd1-cc959c7fa3ca",
                    "url": "https://jlnjajtcnyqupfaqjerz.supabase.co/storage/v1/object/public/app-images/homepage/c18f2b14-16f5-49b6-b7d4-f559ad5632a4/index_hero/1783995994933-u36zhjmc8i.jpg",
                    "sortOrder": 7,
                    "description": "",
                    "isSelected": true,
                    "blockId": null
                  },
                  {
                    "id": "82625b28-31c2-4494-859e-f4469eee0a4b",
                    "url": "https://jlnjajtcnyqupfaqjerz.supabase.co/storage/v1/object/public/app-images/homepage/c18f2b14-16f5-49b6-b7d4-f559ad5632a4/index_hero/1783995995043-cs9ka3ejnh.jpg",
                    "sortOrder": 8,
                    "description": "",
                    "isSelected": true,
                    "blockId": null
                  },
                  {
                    "id": "fc88e785-3640-4b1f-8e22-c765b7d55393",
                    "url": "https://jlnjajtcnyqupfaqjerz.supabase.co/storage/v1/object/public/app-images/homepage/c18f2b14-16f5-49b6-b7d4-f559ad5632a4/index_hero/1783995995143-3ejbff4dx3.jpg",
                    "sortOrder": 9,
                    "description": "",
                    "isSelected": true,
                    "blockId": null
                  }
                ],
                "videos": [ ],
                "mediaType": "image",
                "description": ""
              },
              "closing": {
                "title": "",
                "images": [
                  {
                    "id": "37e33a1f-569e-4d84-9eb6-df91bc99b9bb",
                    "url": "https://jlnjajtcnyqupfaqjerz.supabase.co/storage/v1/object/public/app-images/homepage/c18f2b14-16f5-49b6-b7d4-f559ad5632a4/index_closing/1783999228825-cn9x3xwre3.jpg",
                    "sortOrder": 0,
                    "description": "",
                    "isSelected": true,
                    "blockId": null
                  }
                ],
                "videos": [ ],
                "mediaType": "image",
                "description": ""
              },
              "essence": {
                "title": "자연과 함께 머무는 공간",
                "images": [ ],
                "videos": [ ],
                "mediaType": "image",
                "description": ""
              },
              "gallery": {
                "title": "여행의 즐거움을 더하는 공간",
                "images": [ ],
                "videos": [ ],
                "mediaType": "image",
                "description": ""
              },
              "signature": {
                "title": "",
                "images": [ ],
                "videos": [ ],
                "mediaType": "image",
                "description": ""
              }
            }
          ]
        },
        "directions": {
          "sections": [
            {
              "hero": {
                "title": "",
                "images": [
                  {
                    "id": "f16e4595-4d95-4dee-8219-d5c7ce306d37",
                    "url": "https://jlnjajtcnyqupfaqjerz.supabase.co/storage/v1/object/public/app-images/homepage/c18f2b14-16f5-49b6-b7d4-f559ad5632a4/directions_hero/1784005230412-dujbmeq95j.jpg",
                    "sortOrder": 0,
                    "description": "",
                    "isSelected": true,
                    "blockId": null
                  }
                ]
              },
              "notice": {
                "title": "",
                "description": ""
              }
            }
          ]
        },
        "main": {
          "sections": [
            {
              "hero": {
                "title": "",
                "images": [
                  {
                    "id": "e842eee8-6b43-4576-9e89-16481e9e6038",
                    "url": "https://jlnjajtcnyqupfaqjerz.supabase.co/storage/v1/object/public/app-images/homepage/c18f2b14-16f5-49b6-b7d4-f559ad5632a4/main_hero/1783995995037-qaxu1y3062.jpg",
                    "sortOrder": 0,
                    "description": "",
                    "isSelected": true,
                    "blockId": null
                  },
                  {
                    "id": "a6a313bb-63f9-4ee4-b199-78644db480e5",
                    "url": "https://jlnjajtcnyqupfaqjerz.supabase.co/storage/v1/object/public/app-images/homepage/c18f2b14-16f5-49b6-b7d4-f559ad5632a4/main_hero/1783995995561-yrwiwgocxm.jpg",
                    "sortOrder": 1,
                    "description": "",
                    "isSelected": true,
                    "blockId": null
                  },
                  {
                    "id": "c289428c-bf5d-4f32-9353-1f0a371c9889",
                    "url": "https://jlnjajtcnyqupfaqjerz.supabase.co/storage/v1/object/public/app-images/homepage/c18f2b14-16f5-49b6-b7d4-f559ad5632a4/main_hero/1783995995739-eofagob17a.jpg",
                    "sortOrder": 2,
                    "description": "",
                    "isSelected": true,
                    "blockId": null
                  },
                  {
                    "id": "5aacc59d-5964-48d2-a108-e89560168382",
                    "url": "https://jlnjajtcnyqupfaqjerz.supabase.co/storage/v1/object/public/app-images/homepage/c18f2b14-16f5-49b6-b7d4-f559ad5632a4/main_hero/1783995995228-ddakugdf0u.jpg",
                    "sortOrder": 3,
                    "description": "",
                    "isSelected": true,
                    "blockId": null
                  },
                  {
                    "id": "b5e9757c-1e12-417b-87e4-faa09b5e5698",
                    "url": "https://jlnjajtcnyqupfaqjerz.supabase.co/storage/v1/object/public/app-images/homepage/c18f2b14-16f5-49b6-b7d4-f559ad5632a4/main_hero/1783995995160-i16ts0dvtn.jpg",
                    "sortOrder": 4,
                    "description": "",
                    "isSelected": true,
                    "blockId": null
                  },
                  {
                    "id": "a11abef7-0a5c-4b08-9523-be5bde028993",
                    "url": "https://jlnjajtcnyqupfaqjerz.supabase.co/storage/v1/object/public/app-images/homepage/c18f2b14-16f5-49b6-b7d4-f559ad5632a4/main_hero/1783995994861-jda8lvxm3z.jpg",
                    "sortOrder": 5,
                    "description": "",
                    "isSelected": true,
                    "blockId": null
                  },
                  {
                    "id": "328c4ca3-09b0-4e97-9258-eaf3c492b090",
                    "url": "https://jlnjajtcnyqupfaqjerz.supabase.co/storage/v1/object/public/app-images/homepage/c18f2b14-16f5-49b6-b7d4-f559ad5632a4/main_hero/1783995994858-ycgu2g7jow.jpg",
                    "sortOrder": 6,
                    "description": "",
                    "isSelected": true,
                    "blockId": null
                  },
                  {
                    "id": "e78a58d1-fffd-4e42-99d2-8d9c8f1d12df",
                    "url": "https://jlnjajtcnyqupfaqjerz.supabase.co/storage/v1/object/public/app-images/homepage/c18f2b14-16f5-49b6-b7d4-f559ad5632a4/main_hero/1783995995842-3fjbjiamcc.jpg",
                    "sortOrder": 7,
                    "description": "",
                    "isSelected": true,
                    "blockId": null
                  },
                  {
                    "id": "36e2bb96-03f1-44e3-a3d3-337cbdba5a43",
                    "url": "https://jlnjajtcnyqupfaqjerz.supabase.co/storage/v1/object/public/app-images/homepage/c18f2b14-16f5-49b6-b7d4-f559ad5632a4/main_hero/1783995995835-o76nrlcqqe.jpg",
                    "sortOrder": 8,
                    "description": "",
                    "isSelected": true,
                    "blockId": null
                  },
                  {
                    "id": "c954d6ff-03c3-4152-bdd9-01a322bdbb62",
                    "url": "https://jlnjajtcnyqupfaqjerz.supabase.co/storage/v1/object/public/app-images/homepage/c18f2b14-16f5-49b6-b7d4-f559ad5632a4/main_hero/1783995994663-dlb107wf3n.jpg",
                    "sortOrder": 9,
                    "description": "",
                    "isSelected": true,
                    "blockId": null
                  },
                  {
                    "id": "a9fd44a1-8668-46b2-bba8-7cfcca45ad15",
                    "url": "https://jlnjajtcnyqupfaqjerz.supabase.co/storage/v1/object/public/app-images/homepage/c18f2b14-16f5-49b6-b7d4-f559ad5632a4/main_hero/1783995995324-gtsuixmqc3.jpg",
                    "sortOrder": 10,
                    "description": "",
                    "isSelected": true,
                    "blockId": null
                  },
                  {
                    "id": "74ab6b1e-108e-4b90-912f-fa4206b13336",
                    "url": "https://jlnjajtcnyqupfaqjerz.supabase.co/storage/v1/object/public/app-images/homepage/c18f2b14-16f5-49b6-b7d4-f559ad5632a4/main_hero/1783995995621-j51zd2g1as.jpg",
                    "sortOrder": 11,
                    "description": "",
                    "isSelected": true,
                    "blockId": null
                  }
                ],
                "description": ""
              },
              "about": [
                {
                  "title": "편안함을 품은 풍경",
                  "images": [
                    {
                      "id": "701c511f-7fd2-4991-9823-97f5b48da656",
                      "url": "https://jlnjajtcnyqupfaqjerz.supabase.co/storage/v1/object/public/app-images/homepage/c18f2b14-16f5-49b6-b7d4-f559ad5632a4/main_about/1783998498752-5tbqtzs7n4.jpg",
                      "sortOrder": 0,
                      "description": "",
                      "isSelected": true,
                      "blockId": "5443a568-6caf-49c2-8a02-ccd0d3d980a1"
                    },
                    {
                      "id": "a42aebf7-d5ec-468b-9b15-77ac4337e9fd",
                      "url": "https://jlnjajtcnyqupfaqjerz.supabase.co/storage/v1/object/public/app-images/homepage/c18f2b14-16f5-49b6-b7d4-f559ad5632a4/main_about/1783998498450-3iwqx1wqcm.jpg",
                      "sortOrder": 1,
                      "description": "",
                      "isSelected": true,
                      "blockId": "5443a568-6caf-49c2-8a02-ccd0d3d980a1"
                    },
                    {
                      "id": "3c5289fb-281b-46b4-b302-09abf7c6b0d5",
                      "url": "https://jlnjajtcnyqupfaqjerz.supabase.co/storage/v1/object/public/app-images/homepage/c18f2b14-16f5-49b6-b7d4-f559ad5632a4/main_about/1783998498448-pzu4s6d5g3.jpg",
                      "sortOrder": 2,
                      "description": "",
                      "isSelected": true,
                      "blockId": "5443a568-6caf-49c2-8a02-ccd0d3d980a1"
                    },
                    {
                      "id": "53d54d1c-f02f-4d35-bb5c-57f3bbcb67e3",
                      "url": "https://jlnjajtcnyqupfaqjerz.supabase.co/storage/v1/object/public/app-images/homepage/c18f2b14-16f5-49b6-b7d4-f559ad5632a4/main_about/1783998498734-37yu49the5.jpg",
                      "sortOrder": 3,
                      "description": "",
                      "isSelected": true,
                      "blockId": "5443a568-6caf-49c2-8a02-ccd0d3d980a1"
                    },
                    {
                      "id": "2f7e79c1-83e5-4097-a289-c0dbed2c5fa4",
                      "url": "https://jlnjajtcnyqupfaqjerz.supabase.co/storage/v1/object/public/app-images/homepage/c18f2b14-16f5-49b6-b7d4-f559ad5632a4/main_about/1783998498753-5el5twa0i0.jpg",
                      "sortOrder": 4,
                      "description": "",
                      "isSelected": true,
                      "blockId": "5443a568-6caf-49c2-8a02-ccd0d3d980a1"
                    },
                    {
                      "id": "fdc2ece0-8816-4ba1-a47f-65379c2e1725",
                      "url": "https://jlnjajtcnyqupfaqjerz.supabase.co/storage/v1/object/public/app-images/homepage/c18f2b14-16f5-49b6-b7d4-f559ad5632a4/main_about/1783998498647-c7uqts5fe9.jpg",
                      "sortOrder": 5,
                      "description": "",
                      "isSelected": true,
                      "blockId": "5443a568-6caf-49c2-8a02-ccd0d3d980a1"
                    },
                    {
                      "id": "91cba6b6-34da-4b04-b4a6-28eb8b3e74c8",
                      "url": "https://jlnjajtcnyqupfaqjerz.supabase.co/storage/v1/object/public/app-images/homepage/c18f2b14-16f5-49b6-b7d4-f559ad5632a4/main_about/1783998498737-j3cu2vgsqw.jpg",
                      "sortOrder": 6,
                      "description": "",
                      "isSelected": true,
                      "blockId": "5443a568-6caf-49c2-8a02-ccd0d3d980a1"
                    },
                    {
                      "id": "9c4d52a3-14a8-45dc-9f04-294a01053a2d",
                      "url": "https://jlnjajtcnyqupfaqjerz.supabase.co/storage/v1/object/public/app-images/homepage/c18f2b14-16f5-49b6-b7d4-f559ad5632a4/main_about/1783998498649-j1lj8p3ack.jpg",
                      "sortOrder": 7,
                      "description": "",
                      "isSelected": true,
                      "blockId": "5443a568-6caf-49c2-8a02-ccd0d3d980a1"
                    }
                  ],
                  "blockId": "5443a568-6caf-49c2-8a02-ccd0d3d980a1",
                  "description": ""
                }
              ]
            }
          ]
        },
        "room": [ ],
        "facility": [
          {
            "id": "5992e28f-88fc-4bba-be96-1ec805550cd5",
            "sections": [
              {
                "hero": {
                  "title": "햇살 아래에서 가볍게 물에 몸을 맡기며\n여유롭게 흐르는 시간을 느껴보세요.\n시원한 물결 속에서 편안한 휴식을 즐길 수 있습니다.<br>\n ※ 자세한 내용은 이용안내 페이지 참고 부탁드립니다.\n",
                  "images": [ ]
                },
                "about": {
                  "title": "",
                  "images": [ ]
                },
                "experience": {
                  "features": [ ],
                  "additionalInfos": [ ],
                  "benefits": [ ]
                }
              }
            ]
          },
          {
            "id": "7732b955-3358-4312-b716-d602192010d1",
            "sections": [
              {
                "hero": {
                  "title": "여유로운 공간에서 즐기는 식사 시간은\n단순한 한 끼를 넘어 특별한 기억으로 남습니다.\n편안한 분위기 속에서 온전한 시간을 보내보세요.\n\n ※ 자세한 내용은 이용안내 페이지 참고 부탁드립니다.\n\n",
                  "images": [ ]
                },
                "about": {
                  "title": "",
                  "images": [ ]
                },
                "experience": {
                  "features": [ ],
                  "additionalInfos": [ ],
                  "benefits": [ ]
                }
              }
            ]
          },
          {
            "id": "31d12c77-a27d-4092-9b3e-8f5a2cd31ba8",
            "sections": [
              {
                "hero": {
                  "title": "맛있는 식사와 다양한 즐길 거리가 어우러져\n머무는 시간까지 더욱 특별한 추억으로 이어집니다.\n\n ※ 자세한 내용은 이용안내 페이지 참고 부탁드립니다.\n",
                  "images": [ ]
                },
                "about": {
                  "title": "",
                  "images": [ ]
                },
                "experience": {
                  "features": [ ],
                  "additionalInfos": [ ],
                  "benefits": [ ]
                }
              }
            ]
          },
          {
            "id": "da2185b1-3a7f-4e28-a08b-4bf77eb0364c",
            "sections": [
              {
                "hero": {
                  "title": "머무는 모든 순간이 편안하게 이어질 수 있도록\n세심한 준비로 공간의 완성도를 더했습니다.\n부담 없이 쉬어갈 수 있는 시간을 제공합니다.\n\n ※ 자세한 내용은 이용안내 페이지 참고 부탁드립니다.\n\n",
                  "images": [ ]
                },
                "about": {
                  "title": "",
                  "images": [ ]
                },
                "experience": {
                  "features": [ ],
                  "additionalInfos": [ ],
                  "benefits": [ ]
                }
              }
            ]
          }
        ],
        "reservation": {
          "sections": [
            {
              "hero": {
                "title": "",
                "images": [
                  {
                    "id": "69a11b76-886a-4596-938f-93bab80faa9b",
                    "url": "https://jlnjajtcnyqupfaqjerz.supabase.co/storage/v1/object/public/app-images/homepage/c18f2b14-16f5-49b6-b7d4-f559ad5632a4/reservation_hero/1783997046090-mqi3l6rfro.jpg",
                    "sortOrder": 0,
                    "description": "",
                    "isSelected": true,
                    "blockId": null
                  }
                ]
              },
              "about": {
                "title": "",
                "images": [ ],
                "description": ""
              }
            }
          ]
        },
        "nearbyAttractions": {
          "sections": [
            {
              "hero": {
                "title": "",
                "images": [ ],
                "description": ""
              },
              "about": [ ],
              "enabled": false
            }
          ]
        },
        "layoutMap": {
          "sections": [
            {
              "hero": {
                "title": "",
                "images": [
                  {
                    "id": "1d49bcf1-25c3-4fe4-b7c6-34df7c8b7ffe",
                    "url": "https://jlnjajtcnyqupfaqjerz.supabase.co/storage/v1/object/public/app-images/homepage/c18f2b14-16f5-49b6-b7d4-f559ad5632a4/layout_map_hero/1783996929149-uc323v9hh3.jpg",
                    "sortOrder": 0,
                    "description": "",
                    "isSelected": true,
                    "blockId": null
                  }
                ],
                "description": ""
              },
              "about": {
                "title": "",
                "images": [
                  {
                    "id": "f4610106-e7b5-4305-b762-2be03f9f60f9",
                    "url": "https://jlnjajtcnyqupfaqjerz.supabase.co/storage/v1/object/public/app-images/homepage/c18f2b14-16f5-49b6-b7d4-f559ad5632a4/layout_map_about/1783996929141-605gjdnhlu.jpg",
                    "sortOrder": 0,
                    "description": "",
                    "isSelected": true,
                    "blockId": null
                  }
                ],
                "description": ""
              },
              "enabled": true
            }
          ]
        }
      },
      "popup": {
        "popups": [ ]
      },
      "theme": {
        "font": {
          "koMain": {
            "cdn": "https://cdn.jsdelivr.net/gh/orioncactus/pretendard/dist/web/static/pretendard.min.css",
            "key": "pretendard",
            "woff2": null,
            "family": "Pretendard"
          },
          "koSub": {
            "cdn": "https://cdn.jsdelivr.net/gh/orioncactus/pretendard/dist/web/static/pretendard.min.css",
            "key": "pretendard",
            "woff2": null,
            "family": "Pretendard"
          },
          "enMain": {
            "cdn": "https://fonts.googleapis.com/css2?family=Cormorant:ital,wght@0,300..700;1,300..700&display=swap",
            "key": "cormorant",
            "woff2": null,
            "family": "Cormorant"
          }
        },
        "color": {
          "primary": "#F4F3EB",
          "secondary": "#76805B"
        }
      },
      "property": {
        "name": "가평 온하루펜션",
        "nameEn": "Gapyeong Onharu Pension",
        "images": [
          {
            "id": "f33635dd-f6f8-4378-b7f1-ce995a99c9b6",
            "url": "https://jlnjajtcnyqupfaqjerz.supabase.co/storage/v1/object/public/app-images/homepage/c18f2b14-16f5-49b6-b7d4-f559ad5632a4/property_thumbnail/1783994413559-15dsnle7uz.jpg",
            "sortOrder": 0,
            "description": "",
            "isSelected": true,
            "blockId": null,
            "category": "property_thumbnail"
          },
          {
            "id": "03018796-15b6-4b1f-9036-9be5129d7350",
            "url": "https://jlnjajtcnyqupfaqjerz.supabase.co/storage/v1/object/public/app-images/homepage/c18f2b14-16f5-49b6-b7d4-f559ad5632a4/property_exterior/1783994413678-iy8amnkkoq.jpg",
            "sortOrder": 0,
            "description": "",
            "isSelected": true,
            "blockId": null,
            "category": "property_exterior"
          },
          {
            "id": "ebb8148c-0f6e-433b-b313-0cd5f93ae25a",
            "url": "https://jlnjajtcnyqupfaqjerz.supabase.co/storage/v1/object/public/app-images/homepage/c18f2b14-16f5-49b6-b7d4-f559ad5632a4/property_exterior/1783994413712-o9dpbxggcx.jpg",
            "sortOrder": 1,
            "description": "",
            "isSelected": true,
            "blockId": null,
            "category": "property_exterior"
          },
          {
            "id": "a3dc537e-cc31-40b6-a192-91131cfe30f5",
            "url": "https://jlnjajtcnyqupfaqjerz.supabase.co/storage/v1/object/public/app-images/homepage/c18f2b14-16f5-49b6-b7d4-f559ad5632a4/property_exterior/1783994413866-uqozqdvht8.jpg",
            "sortOrder": 2,
            "description": "",
            "isSelected": true,
            "blockId": null,
            "category": "property_exterior"
          },
          {
            "id": "a4b6ad8f-338b-4a6c-ade7-a7c08c222d46",
            "url": "https://jlnjajtcnyqupfaqjerz.supabase.co/storage/v1/object/public/app-images/homepage/c18f2b14-16f5-49b6-b7d4-f559ad5632a4/property_exterior/1783994413703-mxf9d89j5d.jpg",
            "sortOrder": 3,
            "description": "",
            "isSelected": true,
            "blockId": null,
            "category": "property_exterior"
          },
          {
            "id": "5b7a9bd7-7b76-46a8-bca7-c53369fa88d0",
            "url": "https://jlnjajtcnyqupfaqjerz.supabase.co/storage/v1/object/public/app-images/homepage/c18f2b14-16f5-49b6-b7d4-f559ad5632a4/property_exterior/1783994413947-ajvm6l6ym4.jpg",
            "sortOrder": 4,
            "description": "",
            "isSelected": true,
            "blockId": null,
            "category": "property_exterior"
          },
          {
            "id": "12541367-b67c-4c99-a1e6-2f64d47813c6",
            "url": "https://jlnjajtcnyqupfaqjerz.supabase.co/storage/v1/object/public/app-images/homepage/c18f2b14-16f5-49b6-b7d4-f559ad5632a4/property_exterior/1783994413992-6o0kcdwxao.jpg",
            "sortOrder": 5,
            "description": "",
            "isSelected": true,
            "blockId": null,
            "category": "property_exterior"
          },
          {
            "id": "fb922bae-b0b5-482d-b551-d54ac3ae294d",
            "url": "https://jlnjajtcnyqupfaqjerz.supabase.co/storage/v1/object/public/app-images/homepage/c18f2b14-16f5-49b6-b7d4-f559ad5632a4/property_exterior/1783994413573-h65zeog8ge.jpg",
            "sortOrder": 6,
            "description": "",
            "isSelected": true,
            "blockId": null,
            "category": "property_exterior"
          },
          {
            "id": "d639b557-938f-415d-bae4-4d2a6380f62c",
            "url": "https://jlnjajtcnyqupfaqjerz.supabase.co/storage/v1/object/public/app-images/homepage/c18f2b14-16f5-49b6-b7d4-f559ad5632a4/property_exterior/1783994413986-4rkd508sz9.jpg",
            "sortOrder": 7,
            "description": "",
            "isSelected": true,
            "blockId": null,
            "category": "property_exterior"
          },
          {
            "id": "1185a6ad-6ad4-45d1-9d2b-9d178a80574f",
            "url": "https://jlnjajtcnyqupfaqjerz.supabase.co/storage/v1/object/public/app-images/homepage/c18f2b14-16f5-49b6-b7d4-f559ad5632a4/property_exterior/1783994413688-c8pl2bmhwe.jpg",
            "sortOrder": 8,
            "description": "",
            "isSelected": true,
            "blockId": null,
            "category": "property_exterior"
          },
          {
            "id": "3738fbda-e447-41e6-8aaf-a8e493fb9894",
            "url": "https://jlnjajtcnyqupfaqjerz.supabase.co/storage/v1/object/public/app-images/homepage/c18f2b14-16f5-49b6-b7d4-f559ad5632a4/property_exterior/1783994413671-4n58rqczdi.jpg",
            "sortOrder": 9,
            "description": "",
            "isSelected": true,
            "blockId": null,
            "category": "property_exterior"
          },
          {
            "id": "755c6875-d933-4a7e-8bf2-7a6e4cb592f4",
            "url": "https://jlnjajtcnyqupfaqjerz.supabase.co/storage/v1/object/public/app-images/homepage/c18f2b14-16f5-49b6-b7d4-f559ad5632a4/property_exterior/1783994413507-bacwd91jhn.jpg",
            "sortOrder": 10,
            "description": "",
            "isSelected": true,
            "blockId": null,
            "category": "property_exterior"
          },
          {
            "id": "d184a453-554e-4dbc-865f-dbf46ebbd00a",
            "url": "https://jlnjajtcnyqupfaqjerz.supabase.co/storage/v1/object/public/app-images/homepage/c18f2b14-16f5-49b6-b7d4-f559ad5632a4/property_exterior/1783994414257-a7fyh9u230.jpg",
            "sortOrder": 11,
            "description": "",
            "isSelected": true,
            "blockId": null,
            "category": "property_exterior"
          }
        ]
      },
      "roomtypes": [
        {
          "id": "c0ef986b-42eb-4923-ae70-f5bc6e24d132",
          "images": [
            {
              "id": "186d7ebe-1bcf-44ac-80f9-eb266bdf3b3b",
              "url": "https://jlnjajtcnyqupfaqjerz.supabase.co/storage/v1/object/public/app-images/homepage/c18f2b14-16f5-49b6-b7d4-f559ad5632a4/roomtype_thumbnail/1783995209939-jx3k6d91mi.jpg",
              "sortOrder": 0,
              "description": "",
              "isSelected": true,
              "blockId": "c0ef986b-42eb-4923-ae70-f5bc6e24d132",
              "category": "roomtype_thumbnail"
            },
            {
              "id": "25b8120f-4cca-429e-9a44-dde2207e824b",
              "url": "https://jlnjajtcnyqupfaqjerz.supabase.co/storage/v1/object/public/app-images/homepage/c18f2b14-16f5-49b6-b7d4-f559ad5632a4/roomtype_interior/1783995209956-u7z1pq1ztn.jpg",
              "sortOrder": 0,
              "description": "",
              "isSelected": true,
              "blockId": "c0ef986b-42eb-4923-ae70-f5bc6e24d132",
              "category": "roomtype_interior"
            },
            {
              "id": "5309ac56-8189-4432-9807-22590d308888",
              "url": "https://jlnjajtcnyqupfaqjerz.supabase.co/storage/v1/object/public/app-images/homepage/c18f2b14-16f5-49b6-b7d4-f559ad5632a4/roomtype_interior/1783995209923-i8iy6esb5j.jpg",
              "sortOrder": 1,
              "description": "",
              "isSelected": true,
              "blockId": "c0ef986b-42eb-4923-ae70-f5bc6e24d132",
              "category": "roomtype_interior"
            },
            {
              "id": "bf478c99-bb83-4100-b237-abe312586a99",
              "url": "https://jlnjajtcnyqupfaqjerz.supabase.co/storage/v1/object/public/app-images/homepage/c18f2b14-16f5-49b6-b7d4-f559ad5632a4/roomtype_interior/1783995209925-e0id9xjjb7.jpg",
              "sortOrder": 2,
              "description": "",
              "isSelected": true,
              "blockId": "c0ef986b-42eb-4923-ae70-f5bc6e24d132",
              "category": "roomtype_interior"
            },
            {
              "id": "0fa5e78f-575b-48e4-b92f-fe056ac41e27",
              "url": "https://jlnjajtcnyqupfaqjerz.supabase.co/storage/v1/object/public/app-images/homepage/c18f2b14-16f5-49b6-b7d4-f559ad5632a4/roomtype_interior/1783995209950-fu428exchv.jpg",
              "sortOrder": 3,
              "description": "",
              "isSelected": true,
              "blockId": "c0ef986b-42eb-4923-ae70-f5bc6e24d132",
              "category": "roomtype_interior"
            },
            {
              "id": "0ef0c63a-caa7-4ab8-8e22-edcb902c3607",
              "url": "https://jlnjajtcnyqupfaqjerz.supabase.co/storage/v1/object/public/app-images/homepage/c18f2b14-16f5-49b6-b7d4-f559ad5632a4/roomtype_interior/1783995209999-2o99nm0ft1.jpg",
              "sortOrder": 4,
              "description": "",
              "isSelected": true,
              "blockId": "c0ef986b-42eb-4923-ae70-f5bc6e24d132",
              "category": "roomtype_interior"
            },
            {
              "id": "edcc2da8-f3fb-4fb0-81f8-5e9f18125e6f",
              "url": "https://jlnjajtcnyqupfaqjerz.supabase.co/storage/v1/object/public/app-images/homepage/c18f2b14-16f5-49b6-b7d4-f559ad5632a4/roomtype_interior/1783995210011-l88xj01w96.jpg",
              "sortOrder": 5,
              "description": "",
              "isSelected": true,
              "blockId": "c0ef986b-42eb-4923-ae70-f5bc6e24d132",
              "category": "roomtype_interior"
            },
            {
              "id": "eba4e62b-36e0-4b62-aa42-76cf52b32f02",
              "url": "https://jlnjajtcnyqupfaqjerz.supabase.co/storage/v1/object/public/app-images/homepage/c18f2b14-16f5-49b6-b7d4-f559ad5632a4/roomtype_interior/1783995210080-onwhloi5ss.jpg",
              "sortOrder": 6,
              "description": "",
              "isSelected": true,
              "blockId": "c0ef986b-42eb-4923-ae70-f5bc6e24d132",
              "category": "roomtype_interior"
            },
            {
              "id": "c447985c-42c9-446b-9e2a-c997a3b7004c",
              "url": "https://jlnjajtcnyqupfaqjerz.supabase.co/storage/v1/object/public/app-images/homepage/c18f2b14-16f5-49b6-b7d4-f559ad5632a4/roomtype_interior/1783995209974-97rzaxearu.jpg",
              "sortOrder": 7,
              "description": "",
              "isSelected": true,
              "blockId": "c0ef986b-42eb-4923-ae70-f5bc6e24d132",
              "category": "roomtype_interior"
            },
            {
              "id": "2edab316-d5c2-4c7f-8471-7440898b65b9",
              "url": "https://jlnjajtcnyqupfaqjerz.supabase.co/storage/v1/object/public/app-images/homepage/c18f2b14-16f5-49b6-b7d4-f559ad5632a4/roomtype_interior/1783995210067-apiqmdivbc.jpg",
              "sortOrder": 8,
              "description": "",
              "isSelected": true,
              "blockId": "c0ef986b-42eb-4923-ae70-f5bc6e24d132",
              "category": "roomtype_interior"
            },
            {
              "id": "309b5d5c-ca09-48d5-9657-0f1688c3e2ce",
              "url": "https://jlnjajtcnyqupfaqjerz.supabase.co/storage/v1/object/public/app-images/homepage/c18f2b14-16f5-49b6-b7d4-f559ad5632a4/roomtype_interior/1783995209991-hrr2l8vcku.jpg",
              "sortOrder": 9,
              "description": "",
              "isSelected": true,
              "blockId": "c0ef986b-42eb-4923-ae70-f5bc6e24d132",
              "category": "roomtype_interior"
            },
            {
              "id": "41cffdda-cc14-40b2-af9d-ee69782f1ebd",
              "url": "https://jlnjajtcnyqupfaqjerz.supabase.co/storage/v1/object/public/app-images/homepage/c18f2b14-16f5-49b6-b7d4-f559ad5632a4/roomtype_interior/1783995210113-pohu8v8717.jpg",
              "sortOrder": 10,
              "description": "",
              "isSelected": true,
              "blockId": "c0ef986b-42eb-4923-ae70-f5bc6e24d132",
              "category": "roomtype_interior"
            },
            {
              "id": "71563451-2f03-41c0-bfe2-ed5fceb9c1bc",
              "url": "https://jlnjajtcnyqupfaqjerz.supabase.co/storage/v1/object/public/app-images/homepage/c18f2b14-16f5-49b6-b7d4-f559ad5632a4/roomtype_interior/1783995210174-kwv9vzhabh.jpg",
              "sortOrder": 11,
              "description": "",
              "isSelected": true,
              "blockId": "c0ef986b-42eb-4923-ae70-f5bc6e24d132",
              "category": "roomtype_interior"
            },
            {
              "id": "233dbdd5-387b-48fb-bd23-e25b95936e0e",
              "url": "https://jlnjajtcnyqupfaqjerz.supabase.co/storage/v1/object/public/app-images/homepage/c18f2b14-16f5-49b6-b7d4-f559ad5632a4/roomtype_interior/1783995210184-wibn2qcfjh.jpg",
              "sortOrder": 12,
              "description": "",
              "isSelected": true,
              "blockId": "c0ef986b-42eb-4923-ae70-f5bc6e24d132",
              "category": "roomtype_interior"
            },
            {
              "id": "1f1ac24f-1b34-425d-a7bf-89aaec0e0e7b",
              "url": "https://jlnjajtcnyqupfaqjerz.supabase.co/storage/v1/object/public/app-images/homepage/c18f2b14-16f5-49b6-b7d4-f559ad5632a4/roomtype_interior/1783995210000-ge2m48q7h0.jpg",
              "sortOrder": 13,
              "description": "",
              "isSelected": true,
              "blockId": "c0ef986b-42eb-4923-ae70-f5bc6e24d132",
              "category": "roomtype_interior"
            },
            {
              "id": "e0708357-f9db-4c94-bd24-b3a700bc741a",
              "url": "https://jlnjajtcnyqupfaqjerz.supabase.co/storage/v1/object/public/app-images/homepage/c18f2b14-16f5-49b6-b7d4-f559ad5632a4/roomtype_interior/1783995210277-j8lyz56l5l.jpg",
              "sortOrder": 14,
              "description": "",
              "isSelected": true,
              "blockId": "c0ef986b-42eb-4923-ae70-f5bc6e24d132",
              "category": "roomtype_interior"
            },
            {
              "id": "41e30131-cf86-4e03-8d69-a6cd3d64955e",
              "url": "https://jlnjajtcnyqupfaqjerz.supabase.co/storage/v1/object/public/app-images/homepage/c18f2b14-16f5-49b6-b7d4-f559ad5632a4/roomtype_exterior/1783995210089-mms6d71x7w.jpg",
              "sortOrder": 0,
              "description": "",
              "isSelected": true,
              "blockId": "c0ef986b-42eb-4923-ae70-f5bc6e24d132",
              "category": "roomtype_exterior"
            },
            {
              "id": "1082789d-66b5-4f84-aebe-e10c51478dc2",
              "url": "https://jlnjajtcnyqupfaqjerz.supabase.co/storage/v1/object/public/app-images/homepage/c18f2b14-16f5-49b6-b7d4-f559ad5632a4/roomtype_exterior/1783995209998-68d982cmsc.jpg",
              "sortOrder": 1,
              "description": "",
              "isSelected": true,
              "blockId": "c0ef986b-42eb-4923-ae70-f5bc6e24d132",
              "category": "roomtype_exterior"
            },
            {
              "id": "bf686dd7-3d3c-4423-b06b-e00a1daeb869",
              "url": "https://jlnjajtcnyqupfaqjerz.supabase.co/storage/v1/object/public/app-images/homepage/c18f2b14-16f5-49b6-b7d4-f559ad5632a4/roomtype_exterior/1783995210290-64lfmt4tis.jpg",
              "sortOrder": 2,
              "description": "",
              "isSelected": true,
              "blockId": "c0ef986b-42eb-4923-ae70-f5bc6e24d132",
              "category": "roomtype_exterior"
            },
            {
              "id": "cb33ae12-87ef-4d3b-bf6d-d6e7f5a8d107",
              "url": "https://jlnjajtcnyqupfaqjerz.supabase.co/storage/v1/object/public/app-images/homepage/c18f2b14-16f5-49b6-b7d4-f559ad5632a4/roomtype_exterior/1783995210080-ky8ap8h5mm.jpg",
              "sortOrder": 3,
              "description": "",
              "isSelected": true,
              "blockId": "c0ef986b-42eb-4923-ae70-f5bc6e24d132",
              "category": "roomtype_exterior"
            }
          ]
        },
        {
          "id": "2b5810fe-fc6e-446f-b84d-02f3ae2cfca0",
          "images": [
            {
              "id": "2b322038-28a5-4457-bf4e-93c78a86553a",
              "url": "https://jlnjajtcnyqupfaqjerz.supabase.co/storage/v1/object/public/app-images/homepage/c18f2b14-16f5-49b6-b7d4-f559ad5632a4/roomtype_thumbnail/1783995388289-u61gwg8fz8.jpg",
              "sortOrder": 1,
              "description": "",
              "isSelected": true,
              "blockId": "2b5810fe-fc6e-446f-b84d-02f3ae2cfca0",
              "category": "roomtype_thumbnail"
            },
            {
              "id": "da1a3c16-6ee2-4acb-8726-d9356b9db863",
              "url": "https://jlnjajtcnyqupfaqjerz.supabase.co/storage/v1/object/public/app-images/homepage/c18f2b14-16f5-49b6-b7d4-f559ad5632a4/roomtype_interior/1783995388291-sdgs269rie.jpg",
              "sortOrder": 15,
              "description": "",
              "isSelected": true,
              "blockId": "2b5810fe-fc6e-446f-b84d-02f3ae2cfca0",
              "category": "roomtype_interior"
            },
            {
              "id": "6a0908ea-b916-47c6-aa0b-c3cb1f4b44d0",
              "url": "https://jlnjajtcnyqupfaqjerz.supabase.co/storage/v1/object/public/app-images/homepage/c18f2b14-16f5-49b6-b7d4-f559ad5632a4/roomtype_interior/1783995388298-hgcwwtv12a.jpg",
              "sortOrder": 16,
              "description": "",
              "isSelected": true,
              "blockId": "2b5810fe-fc6e-446f-b84d-02f3ae2cfca0",
              "category": "roomtype_interior"
            },
            {
              "id": "559b171b-97d4-44d5-a524-bb24f1ff660e",
              "url": "https://jlnjajtcnyqupfaqjerz.supabase.co/storage/v1/object/public/app-images/homepage/c18f2b14-16f5-49b6-b7d4-f559ad5632a4/roomtype_interior/1783995388303-e5vv8g8f14.jpg",
              "sortOrder": 17,
              "description": "",
              "isSelected": true,
              "blockId": "2b5810fe-fc6e-446f-b84d-02f3ae2cfca0",
              "category": "roomtype_interior"
            },
            {
              "id": "e3fc8bbd-bd62-4dfb-ab8b-833025240d4c",
              "url": "https://jlnjajtcnyqupfaqjerz.supabase.co/storage/v1/object/public/app-images/homepage/c18f2b14-16f5-49b6-b7d4-f559ad5632a4/roomtype_interior/1783995388385-tgpaogq42s.jpg",
              "sortOrder": 18,
              "description": "",
              "isSelected": true,
              "blockId": "2b5810fe-fc6e-446f-b84d-02f3ae2cfca0",
              "category": "roomtype_interior"
            },
            {
              "id": "b496887b-289a-4b8c-970a-d052db7b37ec",
              "url": "https://jlnjajtcnyqupfaqjerz.supabase.co/storage/v1/object/public/app-images/homepage/c18f2b14-16f5-49b6-b7d4-f559ad5632a4/roomtype_interior/1783995388363-anvn0jjusa.jpg",
              "sortOrder": 19,
              "description": "",
              "isSelected": true,
              "blockId": "2b5810fe-fc6e-446f-b84d-02f3ae2cfca0",
              "category": "roomtype_interior"
            },
            {
              "id": "a6b492e0-48b6-4645-8364-9f34af392104",
              "url": "https://jlnjajtcnyqupfaqjerz.supabase.co/storage/v1/object/public/app-images/homepage/c18f2b14-16f5-49b6-b7d4-f559ad5632a4/roomtype_interior/1783995388302-e9mbd8g5mi.jpg",
              "sortOrder": 20,
              "description": "",
              "isSelected": true,
              "blockId": "2b5810fe-fc6e-446f-b84d-02f3ae2cfca0",
              "category": "roomtype_interior"
            },
            {
              "id": "912d3cd3-862a-45a3-8187-42857f5a821f",
              "url": "https://jlnjajtcnyqupfaqjerz.supabase.co/storage/v1/object/public/app-images/homepage/c18f2b14-16f5-49b6-b7d4-f559ad5632a4/roomtype_interior/1783995388301-nvforaq6u0.jpg",
              "sortOrder": 21,
              "description": "",
              "isSelected": true,
              "blockId": "2b5810fe-fc6e-446f-b84d-02f3ae2cfca0",
              "category": "roomtype_interior"
            },
            {
              "id": "c79f343f-7bf8-48cd-a7ec-03ba7dd34262",
              "url": "https://jlnjajtcnyqupfaqjerz.supabase.co/storage/v1/object/public/app-images/homepage/c18f2b14-16f5-49b6-b7d4-f559ad5632a4/roomtype_interior/1783995388401-omkfw5h7kf.jpg",
              "sortOrder": 22,
              "description": "",
              "isSelected": true,
              "blockId": "2b5810fe-fc6e-446f-b84d-02f3ae2cfca0",
              "category": "roomtype_interior"
            },
            {
              "id": "c7f28708-5300-45ce-83a8-5363cd4e2966",
              "url": "https://jlnjajtcnyqupfaqjerz.supabase.co/storage/v1/object/public/app-images/homepage/c18f2b14-16f5-49b6-b7d4-f559ad5632a4/roomtype_interior/1783995388382-q8ytgrzc04.jpg",
              "sortOrder": 23,
              "description": "",
              "isSelected": true,
              "blockId": "2b5810fe-fc6e-446f-b84d-02f3ae2cfca0",
              "category": "roomtype_interior"
            },
            {
              "id": "a720b5cc-e004-42a5-b6f6-b8cb6d7a6ddc",
              "url": "https://jlnjajtcnyqupfaqjerz.supabase.co/storage/v1/object/public/app-images/homepage/c18f2b14-16f5-49b6-b7d4-f559ad5632a4/roomtype_interior/1783995388373-s3oct4vyjw.jpg",
              "sortOrder": 24,
              "description": "",
              "isSelected": true,
              "blockId": "2b5810fe-fc6e-446f-b84d-02f3ae2cfca0",
              "category": "roomtype_interior"
            },
            {
              "id": "2ccd40d4-6cc3-4e1a-9d1c-4f2fc729d287",
              "url": "https://jlnjajtcnyqupfaqjerz.supabase.co/storage/v1/object/public/app-images/homepage/c18f2b14-16f5-49b6-b7d4-f559ad5632a4/roomtype_interior/1783995388457-320nhq62ne.jpg",
              "sortOrder": 25,
              "description": "",
              "isSelected": true,
              "blockId": "2b5810fe-fc6e-446f-b84d-02f3ae2cfca0",
              "category": "roomtype_interior"
            },
            {
              "id": "0c62e67e-461c-4818-ba40-6b696ff121bc",
              "url": "https://jlnjajtcnyqupfaqjerz.supabase.co/storage/v1/object/public/app-images/homepage/c18f2b14-16f5-49b6-b7d4-f559ad5632a4/roomtype_exterior/1783995388383-mgrgs7cg4p.jpg",
              "sortOrder": 4,
              "description": "",
              "isSelected": true,
              "blockId": "2b5810fe-fc6e-446f-b84d-02f3ae2cfca0",
              "category": "roomtype_exterior"
            },
            {
              "id": "08ad3f45-9215-49c6-b714-b13a6b7b9520",
              "url": "https://jlnjajtcnyqupfaqjerz.supabase.co/storage/v1/object/public/app-images/homepage/c18f2b14-16f5-49b6-b7d4-f559ad5632a4/roomtype_exterior/1783995388478-shd5f515uu.jpg",
              "sortOrder": 5,
              "description": "",
              "isSelected": true,
              "blockId": "2b5810fe-fc6e-446f-b84d-02f3ae2cfca0",
              "category": "roomtype_exterior"
            },
            {
              "id": "aa64118f-6568-4c8b-9b71-b8ddb6d7e149",
              "url": "https://jlnjajtcnyqupfaqjerz.supabase.co/storage/v1/object/public/app-images/homepage/c18f2b14-16f5-49b6-b7d4-f559ad5632a4/roomtype_exterior/1783995388403-mqx9vb4te6.jpg",
              "sortOrder": 6,
              "description": "",
              "isSelected": true,
              "blockId": "2b5810fe-fc6e-446f-b84d-02f3ae2cfca0",
              "category": "roomtype_exterior"
            },
            {
              "id": "b5dc555b-2434-44e0-b824-24b55221086f",
              "url": "https://jlnjajtcnyqupfaqjerz.supabase.co/storage/v1/object/public/app-images/homepage/c18f2b14-16f5-49b6-b7d4-f559ad5632a4/roomtype_exterior/1783995388407-wm7e6kki8w.jpg",
              "sortOrder": 7,
              "description": "",
              "isSelected": true,
              "blockId": "2b5810fe-fc6e-446f-b84d-02f3ae2cfca0",
              "category": "roomtype_exterior"
            }
          ]
        },
        {
          "id": "6cbb9513-a1bc-4dc3-a341-ff7c057ae68d",
          "images": [
            {
              "id": "a22f98f5-6954-461d-8b91-b8bfea2fc3ec",
              "url": "https://jlnjajtcnyqupfaqjerz.supabase.co/storage/v1/object/public/app-images/homepage/c18f2b14-16f5-49b6-b7d4-f559ad5632a4/roomtype_thumbnail/1783999349974-wvz07os68b.jpg",
              "sortOrder": 2,
              "description": "",
              "isSelected": true,
              "blockId": "6cbb9513-a1bc-4dc3-a341-ff7c057ae68d",
              "category": "roomtype_thumbnail"
            },
            {
              "id": "8c89f6a2-6aee-4dc1-9ea7-89da960ed0c9",
              "url": "https://jlnjajtcnyqupfaqjerz.supabase.co/storage/v1/object/public/app-images/homepage/c18f2b14-16f5-49b6-b7d4-f559ad5632a4/roomtype_interior/1783999349997-z2rj5pn8ub.jpg",
              "sortOrder": 26,
              "description": "",
              "isSelected": true,
              "blockId": "6cbb9513-a1bc-4dc3-a341-ff7c057ae68d",
              "category": "roomtype_interior"
            },
            {
              "id": "4ea05953-da3c-4416-9bb9-f8e8f1b80ea9",
              "url": "https://jlnjajtcnyqupfaqjerz.supabase.co/storage/v1/object/public/app-images/homepage/c18f2b14-16f5-49b6-b7d4-f559ad5632a4/roomtype_interior/1783999350037-j8sz1mkw8w.jpg",
              "sortOrder": 27,
              "description": "",
              "isSelected": true,
              "blockId": "6cbb9513-a1bc-4dc3-a341-ff7c057ae68d",
              "category": "roomtype_interior"
            },
            {
              "id": "87fb3d1a-55cd-4c1a-a22f-299bfaeb2c99",
              "url": "https://jlnjajtcnyqupfaqjerz.supabase.co/storage/v1/object/public/app-images/homepage/c18f2b14-16f5-49b6-b7d4-f559ad5632a4/roomtype_interior/1783999350037-lq5qpsl8xt.jpg",
              "sortOrder": 28,
              "description": "",
              "isSelected": true,
              "blockId": "6cbb9513-a1bc-4dc3-a341-ff7c057ae68d",
              "category": "roomtype_interior"
            },
            {
              "id": "a300b127-b4c7-4d84-ab56-20ea9151b92e",
              "url": "https://jlnjajtcnyqupfaqjerz.supabase.co/storage/v1/object/public/app-images/homepage/c18f2b14-16f5-49b6-b7d4-f559ad5632a4/roomtype_interior/1783999350092-2xiypz4sf1.jpg",
              "sortOrder": 29,
              "description": "",
              "isSelected": true,
              "blockId": "6cbb9513-a1bc-4dc3-a341-ff7c057ae68d",
              "category": "roomtype_interior"
            },
            {
              "id": "f650d541-292c-40a9-aa01-c7057917eafe",
              "url": "https://jlnjajtcnyqupfaqjerz.supabase.co/storage/v1/object/public/app-images/homepage/c18f2b14-16f5-49b6-b7d4-f559ad5632a4/roomtype_interior/1783999350177-qjabqxufm9.jpg",
              "sortOrder": 30,
              "description": "",
              "isSelected": true,
              "blockId": "6cbb9513-a1bc-4dc3-a341-ff7c057ae68d",
              "category": "roomtype_interior"
            },
            {
              "id": "95a95413-bfb1-4c78-a6cf-26792958d411",
              "url": "https://jlnjajtcnyqupfaqjerz.supabase.co/storage/v1/object/public/app-images/homepage/c18f2b14-16f5-49b6-b7d4-f559ad5632a4/roomtype_interior/1783999350092-puhn7oxvco.jpg",
              "sortOrder": 31,
              "description": "",
              "isSelected": true,
              "blockId": "6cbb9513-a1bc-4dc3-a341-ff7c057ae68d",
              "category": "roomtype_interior"
            },
            {
              "id": "f3767165-77d9-4814-a980-3227abe48b4d",
              "url": "https://jlnjajtcnyqupfaqjerz.supabase.co/storage/v1/object/public/app-images/homepage/c18f2b14-16f5-49b6-b7d4-f559ad5632a4/roomtype_exterior/1783999350285-9jocgv03kj.jpg",
              "sortOrder": 8,
              "description": "",
              "isSelected": true,
              "blockId": "6cbb9513-a1bc-4dc3-a341-ff7c057ae68d",
              "category": "roomtype_exterior"
            },
            {
              "id": "d0d3fd01-1bef-49f8-ab28-ddee3c7d3dc1",
              "url": "https://jlnjajtcnyqupfaqjerz.supabase.co/storage/v1/object/public/app-images/homepage/c18f2b14-16f5-49b6-b7d4-f559ad5632a4/roomtype_exterior/1783999350098-4xw43hxced.jpg",
              "sortOrder": 9,
              "description": "",
              "isSelected": true,
              "blockId": "6cbb9513-a1bc-4dc3-a341-ff7c057ae68d",
              "category": "roomtype_exterior"
            },
            {
              "id": "684b5269-8133-4a57-91bf-4c7d567e6103",
              "url": "https://jlnjajtcnyqupfaqjerz.supabase.co/storage/v1/object/public/app-images/homepage/c18f2b14-16f5-49b6-b7d4-f559ad5632a4/roomtype_exterior/1783999350198-fjjmf78zkt.jpg",
              "sortOrder": 10,
              "description": "",
              "isSelected": true,
              "blockId": "6cbb9513-a1bc-4dc3-a341-ff7c057ae68d",
              "category": "roomtype_exterior"
            },
            {
              "id": "e4165d3d-05bf-43ac-b76f-c4499bfc9421",
              "url": "https://jlnjajtcnyqupfaqjerz.supabase.co/storage/v1/object/public/app-images/homepage/c18f2b14-16f5-49b6-b7d4-f559ad5632a4/roomtype_exterior/1783999350293-73k4uzz8rh.jpg",
              "sortOrder": 11,
              "description": "",
              "isSelected": true,
              "blockId": "6cbb9513-a1bc-4dc3-a341-ff7c057ae68d",
              "category": "roomtype_exterior"
            }
          ]
        }
      ]
    }
  }
}